jkpackager/__init__.py
jkpackager/__main__.py
jkpackager/metadata.py
jkpackager/packager.py
jkpackager-1.0.4.dist-info/LICENSE.txt
jkpackager-1.0.4.dist-info/METADATA
jkpackager-1.0.4.dist-info/WHEEL
jkpackager-1.0.4.dist-info/entry_points.txt
jkpackager-1.0.4.dist-info/top_level.txt
jkpackager-1.0.4.dist-info/RECORD
